app/__init__.py
app/app.py
app/main.py
llm4time/__init__.py
llm4time/version.py
llm4time/core/__init__.py
llm4time/core/formatter.py
llm4time/core/logging.py
llm4time/core/metrics.py
llm4time/core/prompt.py
llm4time/core/data/__init__.py
llm4time/core/data/imputation.py
llm4time/core/data/loader.py
llm4time/core/data/manager.py
llm4time/core/data/preprocessor.py
llm4time/core/data/sampling.py
llm4time/core/evaluate/__init__.py
llm4time/core/evaluate/metrics.py
llm4time/core/evaluate/statistics.py
llm4time/core/formatting/__init__.py
llm4time/core/formatting/to_array.py
llm4time/core/formatting/to_context.py
llm4time/core/formatting/to_csv.py
llm4time/core/formatting/to_custom.py
llm4time/core/formatting/to_json.py
llm4time/core/formatting/to_markdown.py
llm4time/core/formatting/to_plain.py
llm4time/core/formatting/to_symbol.py
llm4time/core/formatting/to_tsv.py
llm4time/core/formatting/encoders/__init__.py
llm4time/core/formatting/encoders/encode_numeric.py
llm4time/core/formatting/encoders/encode_textual.py
llm4time/core/formatting/encoders/decoders/__init__.py
llm4time/core/formatting/encoders/decoders/decode_numeric.py
llm4time/core/formatting/encoders/decoders/decode_textual.py
llm4time/core/formatting/normalizers/__init__.py
llm4time/core/formatting/normalizers/normalize_missing.py
llm4time/core/formatting/normalizers/denormalizers/__init__.py
llm4time/core/formatting/normalizers/denormalizers/denormalize_missing.py
llm4time/core/formatting/parsers/__init__.py
llm4time/core/formatting/parsers/from_array.py
llm4time/core/formatting/parsers/from_context.py
llm4time/core/formatting/parsers/from_csv.py
llm4time/core/formatting/parsers/from_custom.py
llm4time/core/formatting/parsers/from_json.py
llm4time/core/formatting/parsers/from_markdown.py
llm4time/core/formatting/parsers/from_plain.py
llm4time/core/formatting/parsers/from_symbol.py
llm4time/core/formatting/parsers/from_tsv.py
llm4time/core/models/__init__.py
llm4time/core/models/azure.py
llm4time-0.4.2.dist-info/licenses/LICENSE
llm4time-0.4.2.dist-info/METADATA
llm4time-0.4.2.dist-info/WHEEL
llm4time-0.4.2.dist-info/top_level.txt
llm4time-0.4.2.dist-info/RECORD
