Metadata-Version: 2.4
Name: llm4time
Version: 0.4.2
Summary: Um pacote para previsão de séries temporais usando modelos de linguagem.
Home-page: https://github.com/zairobastos/LLM4Time
Author: Zairo Bastos
Author-email: zairobastos@gmail.com
License: MIT License
Keywords: time series,forecasting,LLM,large language models
Requires-Python: >=3.10
License-File: LICENSE
Requires-Dist: lmstudio==1.3.0
Requires-Dist: numpy<2.2.5,>=1.23.0
Requires-Dist: openai<1.86.0,>=1.40.0
Requires-Dist: openpyxl<3.2.0,>=3.1.0
Requires-Dist: pandas<2.2.3,>=2.0.0
Requires-Dist: permetrics<2.0.0,>=1.5.0
Requires-Dist: plotly<6.1.0,>=5.15.0
Requires-Dist: scikit-learn<1.7.1,>=1.3.0
Requires-Dist: scipy<1.15.3,>=1.10.0
Requires-Dist: statsmodels<0.14.5,>=0.14.0
Dynamic: author
Dynamic: author-email
Dynamic: description
Dynamic: description-content-type
Dynamic: home-page
Dynamic: keywords
Dynamic: license
Dynamic: license-file
Dynamic: requires-dist
Dynamic: requires-python
Dynamic: summary
